newstore.json_encoder-1.0.4-py3.8-nspkg.pth
newstore/json_encoder/__init__.py
newstore/json_encoder/encoder.py
newstore.json_encoder-1.0.4.dist-info/LICENSE
newstore.json_encoder-1.0.4.dist-info/METADATA
newstore.json_encoder-1.0.4.dist-info/WHEEL
newstore.json_encoder-1.0.4.dist-info/namespace_packages.txt
newstore.json_encoder-1.0.4.dist-info/top_level.txt
newstore.json_encoder-1.0.4.dist-info/zip-safe
newstore.json_encoder-1.0.4.dist-info/RECORD
