Metadata-Version: 2.1
Name: newstore.json-encoder
Version: 1.0.4
Summary: JSONEncoder
Home-page: https://github.com/NewStore-oss/json-encoder
Author: NewStore Inc.
Author-email: dev@newstore.com
License: UNKNOWN
Platform: UNKNOWN
Requires-Python: >=3.6,<3.9
Requires-Dist: setuptools
